{"cameraMode":{"drawMode":0,"name":"Shaded","section":"Shading Mode"},"sceneLighting":false,"audioPlay":false,"sceneViewState":{"m_AlwaysRefresh":false,"showFog":true,"showSkybox":false,"showFlares":true,"showImageEffects":true,"showParticleSystems":true,"showVisualEffectGraphs":true,"m_FxEnabled":true},"in2DMode":false,"pivot":{"x":2.440070629119873,"y":-10.843990325927735,"z":16.619617462158204},"rotation":{"x":-0.11629817634820938,"y":-0.7877722978591919,"z":0.15682107210159303,"w":-0.5842118263244629},"size":2.582003593444824,"orthographic":false}